{
    "beautify JSON": "cmd + shift + j",
    "total_interview": 568,
    "npg": 5,
    "init_time": 44601.42054398148,
    "last_timevalue": 44999.41963,
    "last_no": 823,
    "number_of_checked_in": 19,
    "number_of_not_check_in": 0,
    "next_group": [],
    "number_of_people_interviewed": 774,
    "file_name": 165,
    "current_lineup": [
        {
            "No": 75,
            "\u4e2d\u6587\u59d3\u540d": "\u9673\u96c5\u6069",
            "timevalue": "2025-03-09 19:25:30"
        }
    ],
    "interviewed": [
        1,
        2,
        3,
        4,
        5,
        6,
        560,
        561,
        562,
        563,
        564,
        565,
        566,
        567,
        568,
        7,
        8,
        9,
        10,
        75
    ],
    "lineup_history": [
        {
            "group_number": 1,
            "people": [
                {
                    "No": 568,
                    "\u4e2d\u6587\u59d3\u540d": "\u59da\u6c90\u8fb0",
                    "timevalue": "2025-03-09 18:48:29"
                },
                {
                    "No": 567,
                    "\u4e2d\u6587\u59d3\u540d": "\u8bb8\u6db5",
                    "timevalue": "2025-03-09 18:48:31"
                },
                {
                    "No": 566,
                    "\u4e2d\u6587\u59d3\u540d": "\u9ec3\u73a5\u7020",
                    "timevalue": "2025-03-09 18:48:33"
                },
                {
                    "No": 565,
                    "\u4e2d\u6587\u59d3\u540d": "\u9ec3\u73fd\u88d5",
                    "timevalue": "2025-03-09 18:48:35"
                },
                {
                    "No": 564,
                    "\u4e2d\u6587\u59d3\u540d": "\u9127\u51f1\u5d50",
                    "timevalue": "2025-03-09 18:48:36"
                },
                {
                    "No": 1,
                    "\u4e2d\u6587\u59d3\u540d": "\u9673\u5955\u9716",
                    "timevalue": "2025-03-09 18:48:48",
                    "latecomer": true
                }
            ],
            "npg": 5
        },
        {
            "group_number": 2,
            "people": [
                {
                    "No": 563,
                    "\u4e2d\u6587\u59d3\u540d": NaN,
                    "timevalue": "2025-03-09 18:48:36"
                },
                {
                    "No": 562,
                    "\u4e2d\u6587\u59d3\u540d": "\u856d\u5d50",
                    "timevalue": "2025-03-09 18:48:38"
                },
                {
                    "No": 561,
                    "\u4e2d\u6587\u59d3\u540d": "\u6f58\u4fca\u7693",
                    "timevalue": "2025-03-09 18:48:41"
                },
                {
                    "No": 5,
                    "\u4e2d\u6587\u59d3\u540d": "\u912d\u5b87\u6674",
                    "timevalue": "2025-03-09 18:48:53",
                    "latecomer": true
                }
            ],
            "npg": 3
        },
        {
            "group_number": 3,
            "people": [
                {
                    "No": 560,
                    "\u4e2d\u6587\u59d3\u540d": "\u5e03\u99ff\u6a02",
                    "timevalue": "2025-03-09 18:48:42"
                },
                {
                    "No": 2,
                    "\u4e2d\u6587\u59d3\u540d": "\u9673\u6cd3\u7fb2",
                    "timevalue": "2025-03-09 18:48:49"
                },
                {
                    "No": 3,
                    "\u4e2d\u6587\u59d3\u540d": "\u66fe\u5955\u8fb0",
                    "timevalue": "2025-03-09 18:48:51"
                },
                {
                    "No": 4,
                    "\u4e2d\u6587\u59d3\u540d": "\u912d\u5c1a\u6615",
                    "timevalue": "2025-03-09 18:48:52"
                },
                {
                    "No": 6,
                    "\u4e2d\u6587\u59d3\u540d": "\u8449\u5343\u745c",
                    "timevalue": "2025-03-09 18:48:55"
                }
            ],
            "npg": 5
        },
        {
            "group_number": 4,
            "people": [
                {
                    "No": 7,
                    "\u4e2d\u6587\u59d3\u540d": "\u9ece\u601d\u6f84",
                    "timevalue": "2025-03-09 18:48:55"
                },
                {
                    "No": 8,
                    "\u4e2d\u6587\u59d3\u540d": "\u674e\u661f\u6cd3",
                    "timevalue": "2025-03-09 18:48:56"
                },
                {
                    "No": 9,
                    "\u4e2d\u6587\u59d3\u540d": "\u674e\u5353\u71c3",
                    "timevalue": "2025-03-09 18:48:57"
                },
                {
                    "No": 10,
                    "\u4e2d\u6587\u59d3\u540d": "\u674e\u4f9d\u71c3",
                    "timevalue": "2025-03-09 18:48:58"
                }
            ],
            "npg": 5
        },
        {
            "group_number": 5,
            "people": [
                {
                    "No": 75,
                    "\u4e2d\u6587\u59d3\u540d": "\u9673\u96c5\u6069",
                    "timevalue": "2025-03-09 19:25:30"
                }
            ],
            "npg": 5
        }
    ],
    "last_front_color": "#ee6b6e"
}